setup.py
nsq/__init__.py
nsq/_compat.py
nsq/async.py
nsq/backoff_timer.py
nsq/client.py
nsq/deflate_socket.py
nsq/event.py
nsq/legacy_reader.py
nsq/message.py
nsq/protocol.py
nsq/reader.py
nsq/snappy_socket.py
nsq/sync.py
nsq/version.py
nsq/writer.py
pynsq.egg-info/PKG-INFO
pynsq.egg-info/SOURCES.txt
pynsq.egg-info/dependency_links.txt
pynsq.egg-info/not-zip-safe
pynsq.egg-info/requires.txt
pynsq.egg-info/top_level.txt