Metadata-Version: 1.1
Name: pynsq
Version: 0.8.2
Summary: official Python client library for NSQ
Home-page: https://github.com/nsqio/pynsq
Author: Matt Reiferson
Author-email: snakes@gmail.com
License: UNKNOWN
Download-URL: https://s3.amazonaws.com/bitly-downloads/nsq/pynsq-0.8.2.tar.gz
Keywords: python nsq
Platform: UNKNOWN
Classifier: Development Status :: 6 - Mature
Classifier: License :: OSI Approved :: MIT License
Classifier: Programming Language :: Python :: 2
Classifier: Programming Language :: Python :: 2.6
Classifier: Programming Language :: Python :: 2.7
Classifier: Programming Language :: Python :: Implementation :: CPython
